pipeline_monitor/__init__.py
pipeline_monitor-1.0.1.dist-info/DESCRIPTION.rst
pipeline_monitor-1.0.1.dist-info/METADATA
pipeline_monitor-1.0.1.dist-info/RECORD
pipeline_monitor-1.0.1.dist-info/WHEEL
pipeline_monitor-1.0.1.dist-info/metadata.json
pipeline_monitor-1.0.1.dist-info/top_level.txt
