Metadata-Version: 2.0
Name: pipeline-monitor
Version: 1.0.1
Summary: PipelineAI Monitor
Home-page: https://github.com/PipelineAI/
Author: Chris Fregly
Author-email: github@pipeline.ai
License: UNKNOWN
Platform: UNKNOWN
Requires-Dist: prometheus-client (==0.0.21)
